[
    {
        "name": "civic-gris",
        "filePath": "galeria-carros/civic-gris.jpg"
    },
    {
        "name": "corolla-azul",
        "filePath": "galeria-carros/corolla-azul.jpg"
    },
    {
        "name": "crv-roja",
        "filePath": "galeria-carros/crv-roja.jpg"
    },
    {
        "name": "explorer",
        "filePath": "galeria-carros/explorel.jpg"
    },
    {
        "name": "fit-negro",
        "filePath": "galeria-carros/fit-negro.jpg"
    },
    {
        "name": "k5",
        "filePath": "galeria-carros/k5.jpg"
    }
]